odoo/addons/nsca_client/README.rst
odoo/addons/nsca_client/__init__.py
odoo/addons/nsca_client/__manifest__.py
odoo/addons/nsca_client/demo/demo_data.xml
odoo/addons/nsca_client/i18n/fr.po
odoo/addons/nsca_client/i18n/nsca_client.pot
odoo/addons/nsca_client/models/__init__.py
odoo/addons/nsca_client/models/nsca_check.py
odoo/addons/nsca_client/models/nsca_server.py
odoo/addons/nsca_client/security/ir.model.access.csv
odoo/addons/nsca_client/static/description/check.png
odoo/addons/nsca_client/static/description/icon.png
odoo/addons/nsca_client/static/description/server.png
odoo/addons/nsca_client/tests/__init__.py
odoo/addons/nsca_client/tests/test_nsca.py
odoo/addons/nsca_client/views/nsca_check.xml
odoo/addons/nsca_client/views/nsca_menu.xml
odoo/addons/nsca_client/views/nsca_server.xml
odoo11_addon_nsca_client-11.0.1.0.0.99.dev11.dist-info/METADATA
odoo11_addon_nsca_client-11.0.1.0.0.99.dev11.dist-info/WHEEL
odoo11_addon_nsca_client-11.0.1.0.0.99.dev11.dist-info/top_level.txt
odoo11_addon_nsca_client-11.0.1.0.0.99.dev11.dist-info/RECORD
